[{"duration": 0.002260258, "chessboard-width": 8, "solutions": 92, "language": "Ruby", "source": "Queen.rb", "url": "https://www.ruby-lang.org/en", "distribution": "Ruby", "version": "Ruby 2.3.0"}, {"duration": 0.017019955, "chessboard-width": 9, "solutions": 352, "language": "Ruby", "source": "Queen.rb", "url": "https://www.ruby-lang.org/en", "distribution": "Ruby", "version": "Ruby 2.3.0"}, {"duration": 0.076365781, "chessboard-width": 10, "solutions": 724, "language": "Ruby", "source": "Queen.rb", "url": "https://www.ruby-lang.org/en", "distribution": "Ruby", "version": "Ruby 2.3.0"}, {"duration": 0.296894735, "chessboard-width": 11, "solutions": 2680, "language": "Ruby", "source": "Queen.rb", "url": "https://www.ruby-lang.org/en", "distribution": "Ruby", "version": "Ruby 2.3.0"}, {"duration": 1.050940633, "chessboard-width": 12, "solutions": 14200, "language": "Ruby", "source": "Queen.rb", "url": "https://www.ruby-lang.org/en", "distribution": "Ruby", "version": "Ruby 2.3.0"}, {"duration": 5.94508109, "chessboard-width": 13, "solutions": 73712, "language": "Ruby", "source": "Queen.rb", "url": "https://www.ruby-lang.org/en", "distribution": "Ruby", "version": "Ruby 2.3.0"}, {"duration": 35.70416681, "chessboard-width": 14, "solutions": 365596, "language": "Ruby", "source": "Queen.rb", "url": "https://www.ruby-lang.org/en", "distribution": "Ruby", "version": "Ruby 2.3.0"}, {"duration": 0.0, "chessboard-width": 8, "solutions": 92, "language": "D", "source": "Queen.d", "url": "https://dlang.org", "distribution": "D (DMD)", "version": "dmd-2.072"}, {"duration": 0.0, "chessboard-width": 9, "solutions": 352, "language": "D", "source": "Queen.d", "url": "https://dlang.org", "distribution": "D (DMD)", "version": "dmd-2.072"}, {"duration": 0.004, "chessboard-width": 10, "solutions": 724, "language": "D", "source": "Queen.d", "url": "https://dlang.org", "distribution": "D (DMD)", "version": "dmd-2.072"}, {"duration": 0.092, "chessboard-width": 11, "solutions": 2680, "language": "D", "source": "Queen.d", "url": "https://dlang.org", "distribution": "D (DMD)", "version": "dmd-2.072"}, {"duration": 0.173, "chessboard-width": 12, "solutions": 14200, "language": "D", "source": "Queen.d", "url": "https://dlang.org", "distribution": "D (DMD)", "version": "dmd-2.072"}, {"duration": 0.577, "chessboard-width": 13, "solutions": 73712, "language": "D", "source": "Queen.d", "url": "https://dlang.org", "distribution": "D (DMD)", "version": "dmd-2.072"}, {"duration": 2.768, "chessboard-width": 14, "solutions": 365596, "language": "D", "source": "Queen.d", "url": "https://dlang.org", "distribution": "D (DMD)", "version": "dmd-2.072"}, {"duration": 16.671, "chessboard-width": 15, "solutions": 2279184, "language": "D", "source": "Queen.d", "url": "https://dlang.org", "distribution": "D (DMD)", "version": "dmd-2.072"}, {"duration": 112.155, "chessboard-width": 16, "solutions": 14772512, "language": "D", "source": "Queen.d", "url": "https://dlang.org", "distribution": "D (DMD)", "version": "dmd-2.072"}, {"duration": 0.006, "chessboard-width": 8, "solutions": 92, "language": "Java", "source": "Queen.java", "url": "http://openjdk.java.net/", "distribution": "OpenJDK", "version": "Java 1.8"}, {"duration": 0.012, "chessboard-width": 9, "solutions": 352, "language": "Java", "source": "Queen.java", "url": "http://openjdk.java.net/", "distribution": "OpenJDK", "version": "Java 1.8"}, {"duration": 0.021, "chessboard-width": 10, "solutions": 724, "language": "Java", "source": "Queen.java", "url": "http://openjdk.java.net/", "distribution": "OpenJDK", "version": "Java 1.8"}, {"duration": 0.056, "chessboard-width": 11, "solutions": 2680, "language": "Java", "source": "Queen.java", "url": "http://openjdk.java.net/", "distribution": "OpenJDK", "version": "Java 1.8"}, {"duration": 0.183, "chessboard-width": 12, "solutions": 14200, "language": "Java", "source": "Queen.java", "url": "http://openjdk.java.net/", "distribution": "OpenJDK", "version": "Java 1.8"}, {"duration": 0.84, "chessboard-width": 13, "solutions": 73712, "language": "Java", "source": "Queen.java", "url": "http://openjdk.java.net/", "distribution": "OpenJDK", "version": "Java 1.8"}, {"duration": 5.084, "chessboard-width": 14, "solutions": 365596, "language": "Java", "source": "Queen.java", "url": "http://openjdk.java.net/", "distribution": "OpenJDK", "version": "Java 1.8"}, {"duration": 42.624, "chessboard-width": 15, "solutions": 2279184, "language": "Java", "source": "Queen.java", "url": "http://openjdk.java.net/", "distribution": "OpenJDK", "version": "Java 1.8"}, {"duration": 0.0001311302185058594, "chessboard-width": 8, "solutions": 92, "language": "FreeBASIC", "source": "Queen.bas", "url": "http://www.freebasic.net", "distribution": "FreeBASIC", "version": "fbc 1.05.0"}, {"duration": 0.0005469322204589844, "chessboard-width": 9, "solutions": 352, "language": "FreeBASIC", "source": "Queen.bas", "url": "http://www.freebasic.net", "distribution": "FreeBASIC", "version": "fbc 1.05.0"}, {"duration": 0.002504825592041016, "chessboard-width": 10, "solutions": 724, "language": "FreeBASIC", "source": "Queen.bas", "url": "http://www.freebasic.net", "distribution": "FreeBASIC", "version": "fbc 1.05.0"}, {"duration": 0.03188896179199219, "chessboard-width": 11, "solutions": 2680, "language": "FreeBASIC", "source": "Queen.bas", "url": "http://www.freebasic.net", "distribution": "FreeBASIC", "version": "fbc 1.05.0"}, {"duration": 0.1326248645782471, "chessboard-width": 12, "solutions": 14200, "language": "FreeBASIC", "source": "Queen.bas", "url": "http://www.freebasic.net", "distribution": "FreeBASIC", "version": "fbc 1.05.0"}, {"duration": 1.583334922790527, "chessboard-width": 13, "solutions": 73712, "language": "FreeBASIC", "source": "Queen.bas", "url": "http://www.freebasic.net", "distribution": "FreeBASIC", "version": "fbc 1.05.0"}, {"duration": 5.090039014816284, "chessboard-width": 14, "solutions": 365596, "language": "FreeBASIC", "source": "Queen.bas", "url": "http://www.freebasic.net", "distribution": "FreeBASIC", "version": "fbc 1.05.0"}, {"duration": 34.5185661315918, "chessboard-width": 15, "solutions": 2279184, "language": "FreeBASIC", "source": "Queen.bas", "url": "http://www.freebasic.net", "distribution": "FreeBASIC", "version": "fbc 1.05.0"}, {"duration": 218.3253200054169, "chessboard-width": 16, "solutions": 14772512, "language": "FreeBASIC", "source": "Queen.bas", "url": "http://www.freebasic.net", "distribution": "FreeBASIC", "version": "fbc 1.05.0"}, {"duration": 0.022054, "chessboard-width": 8, "solutions": 92, "language": "Python", "source": "Queen.py", "url": "http://pypy.org", "distribution": "PyPy", "version": "pypy 5.x"}, {"duration": 0.089388, "chessboard-width": 9, "solutions": 352, "language": "Python", "source": "Queen.py", "url": "http://pypy.org", "distribution": "PyPy", "version": "pypy 5.x"}, {"duration": 0.165411, "chessboard-width": 10, "solutions": 724, "language": "Python", "source": "Queen.py", "url": "http://pypy.org", "distribution": "PyPy", "version": "pypy 5.x"}, {"duration": 0.158438, "chessboard-width": 11, "solutions": 2680, "language": "Python", "source": "Queen.py", "url": "http://pypy.org", "distribution": "PyPy", "version": "pypy 5.x"}, {"duration": 0.225403, "chessboard-width": 12, "solutions": 14200, "language": "Python", "source": "Queen.py", "url": "http://pypy.org", "distribution": "PyPy", "version": "pypy 5.x"}, {"duration": 0.94511, "chessboard-width": 13, "solutions": 73712, "language": "Python", "source": "Queen.py", "url": "http://pypy.org", "distribution": "PyPy", "version": "pypy 5.x"}, {"duration": 3.95984, "chessboard-width": 14, "solutions": 365596, "language": "Python", "source": "Queen.py", "url": "http://pypy.org", "distribution": "PyPy", "version": "pypy 5.x"}, {"duration": 25.980263, "chessboard-width": 15, "solutions": 2279184, "language": "Python", "source": "Queen.py", "url": "http://pypy.org", "distribution": "PyPy", "version": "pypy 5.x"}, {"duration": 0.0023698806762695, "chessboard-width": 8, "solutions": 92, "language": "PHP", "source": "Queen.php", "url": "https://secure.php.net", "distribution": "PHP", "version": "PHP 5.6"}, {"duration": 0.068099975585938, "chessboard-width": 9, "solutions": 352, "language": "PHP", "source": "Queen.php", "url": "https://secure.php.net", "distribution": "PHP", "version": "PHP 5.6"}, {"duration": 0.041280031204224, "chessboard-width": 10, "solutions": 724, "language": "PHP", "source": "Queen.php", "url": "https://secure.php.net", "distribution": "PHP", "version": "PHP 5.6"}, {"duration": 0.25742101669312, "chessboard-width": 11, "solutions": 2680, "language": "PHP", "source": "Queen.php", "url": "https://secure.php.net", "distribution": "PHP", "version": "PHP 5.6"}, {"duration": 0.98229479789734, "chessboard-width": 12, "solutions": 14200, "language": "PHP", "source": "Queen.php", "url": "https://secure.php.net", "distribution": "PHP", "version": "PHP 5.6"}, {"duration": 6.1908190250397, "chessboard-width": 13, "solutions": 73712, "language": "PHP", "source": "Queen.php", "url": "https://secure.php.net", "distribution": "PHP", "version": "PHP 5.6"}, {"duration": 47.70192694664, "chessboard-width": 14, "solutions": 365596, "language": "PHP", "source": "Queen.php", "url": "https://secure.php.net", "distribution": "PHP", "version": "PHP 5.6"}, {"duration": 0.005, "chessboard-width": 8, "solutions": 92, "language": "CLisp", "source": "Queen.lisp", "url": "http://www.sbcl.org/", "distribution": "Steel Bank", "version": "sbcl-1.3.12"}, {"duration": 0.01, "chessboard-width": 9, "solutions": 352, "language": "CLisp", "source": "Queen.lisp", "url": "http://www.sbcl.org/", "distribution": "Steel Bank", "version": "sbcl-1.3.12"}, {"duration": 0.174, "chessboard-width": 10, "solutions": 724, "language": "CLisp", "source": "Queen.lisp", "url": "http://www.sbcl.org/", "distribution": "Steel Bank", "version": "sbcl-1.3.12"}, {"duration": 0.28, "chessboard-width": 11, "solutions": 2680, "language": "CLisp", "source": "Queen.lisp", "url": "http://www.sbcl.org/", "distribution": "Steel Bank", "version": "sbcl-1.3.12"}, {"duration": 0.907, "chessboard-width": 12, "solutions": 14200, "language": "CLisp", "source": "Queen.lisp", "url": "http://www.sbcl.org/", "distribution": "Steel Bank", "version": "sbcl-1.3.12"}, {"duration": 5.112, "chessboard-width": 13, "solutions": 73712, "language": "CLisp", "source": "Queen.lisp", "url": "http://www.sbcl.org/", "distribution": "Steel Bank", "version": "sbcl-1.3.12"}, {"duration": 30.646, "chessboard-width": 14, "solutions": 365596, "language": "CLisp", "source": "Queen.lisp", "url": "http://www.sbcl.org/", "distribution": "Steel Bank", "version": "sbcl-1.3.12"}, {"duration": 0.000302, "chessboard-width": 8, "solutions": 92, "language": "Go", "source": "Queen.go", "url": "https://golang.org", "distribution": "Google Go", "version": "Go 1.7.4"}, {"duration": 0.000674, "chessboard-width": 9, "solutions": 352, "language": "Go", "source": "Queen.go", "url": "https://golang.org", "distribution": "Google Go", "version": "Go 1.7.4"}, {"duration": 0.003133, "chessboard-width": 10, "solutions": 724, "language": "Go", "source": "Queen.go", "url": "https://golang.org", "distribution": "Google Go", "version": "Go 1.7.4"}, {"duration": 0.039134, "chessboard-width": 11, "solutions": 2680, "language": "Go", "source": "Queen.go", "url": "https://golang.org", "distribution": "Google Go", "version": "Go 1.7.4"}, {"duration": 0.157352, "chessboard-width": 12, "solutions": 14200, "language": "Go", "source": "Queen.go", "url": "https://golang.org", "distribution": "Google Go", "version": "Go 1.7.4"}, {"duration": 0.686377, "chessboard-width": 13, "solutions": 73712, "language": "Go", "source": "Queen.go", "url": "https://golang.org", "distribution": "Google Go", "version": "Go 1.7.4"}, {"duration": 2.624682, "chessboard-width": 14, "solutions": 365596, "language": "Go", "source": "Queen.go", "url": "https://golang.org", "distribution": "Google Go", "version": "Go 1.7.4"}, {"duration": 16.188268, "chessboard-width": 15, "solutions": 2279184, "language": "Go", "source": "Queen.go", "url": "https://golang.org", "distribution": "Google Go", "version": "Go 1.7.4"}, {"duration": 108.03436, "chessboard-width": 16, "solutions": 14772512, "language": "Go", "source": "Queen.go", "url": "https://golang.org", "distribution": "Google Go", "version": "Go 1.7.4"}, {"duration": 0.074, "chessboard-width": 8, "solutions": 92, "language": "Groovy", "source": "Queen.groovy", "url": "http://groovy-lang.org/", "distribution": "Groovy", "version": "Groovy 2.4.7"}, {"duration": 0.144, "chessboard-width": 9, "solutions": 352, "language": "Groovy", "source": "Queen.groovy", "url": "http://groovy-lang.org/", "distribution": "Groovy", "version": "Groovy 2.4.7"}, {"duration": 0.26, "chessboard-width": 10, "solutions": 724, "language": "Groovy", "source": "Queen.groovy", "url": "http://groovy-lang.org/", "distribution": "Groovy", "version": "Groovy 2.4.7"}, {"duration": 0.487, "chessboard-width": 11, "solutions": 2680, "language": "Groovy", "source": "Queen.groovy", "url": "http://groovy-lang.org/", "distribution": "Groovy", "version": "Groovy 2.4.7"}, {"duration": 1.482, "chessboard-width": 12, "solutions": 14200, "language": "Groovy", "source": "Queen.groovy", "url": "http://groovy-lang.org/", "distribution": "Groovy", "version": "Groovy 2.4.7"}, {"duration": 11.865, "chessboard-width": 13, "solutions": 73712, "language": "Groovy", "source": "Queen.groovy", "url": "http://groovy-lang.org/", "distribution": "Groovy", "version": "Groovy 2.4.7"}, {"duration": 0.001, "chessboard-width": 9, "solutions": 352, "language": "C#", "source": "Queen.css", "url": "http://www.mono-project.com/", "distribution": "Mono", "version": "Mono 4.6"}, {"duration": 0.004, "chessboard-width": 10, "solutions": 724, "language": "C#", "source": "Queen.css", "url": "http://www.mono-project.com/", "distribution": "Mono", "version": "Mono 4.6"}, {"duration": 0.03, "chessboard-width": 11, "solutions": 2680, "language": "C#", "source": "Queen.css", "url": "http://www.mono-project.com/", "distribution": "Mono", "version": "Mono 4.6"}, {"duration": 0.128, "chessboard-width": 12, "solutions": 14200, "language": "C#", "source": "Queen.css", "url": "http://www.mono-project.com/", "distribution": "Mono", "version": "Mono 4.6"}, {"duration": 0.779, "chessboard-width": 13, "solutions": 73712, "language": "C#", "source": "Queen.css", "url": "http://www.mono-project.com/", "distribution": "Mono", "version": "Mono 4.6"}, {"duration": 4.558, "chessboard-width": 14, "solutions": 365596, "language": "C#", "source": "Queen.css", "url": "http://www.mono-project.com/", "distribution": "Mono", "version": "Mono 4.6"}, {"duration": 39.269, "chessboard-width": 15, "solutions": 2279184, "language": "C#", "source": "Queen.css", "url": "http://www.mono-project.com/", "distribution": "Mono", "version": "Mono 4.6"}, {"duration": 0.01, "chessboard-width": 11, "solutions": 2680, "language": "C++", "source": "Queen.cxx", "url": "https://gcc.gnu.org", "distribution": "GNU GCC", "version": "gcc 5.x"}, {"duration": 0.07, "chessboard-width": 12, "solutions": 14200, "language": "C++", "source": "Queen.cxx", "url": "https://gcc.gnu.org", "distribution": "GNU GCC", "version": "gcc 5.x"}, {"duration": 0.38, "chessboard-width": 13, "solutions": 73712, "language": "C++", "source": "Queen.cxx", "url": "https://gcc.gnu.org", "distribution": "GNU GCC", "version": "gcc 5.x"}, {"duration": 2.23, "chessboard-width": 14, "solutions": 365596, "language": "C++", "source": "Queen.cxx", "url": "https://gcc.gnu.org", "distribution": "GNU GCC", "version": "gcc 5.x"}, {"duration": 13.55, "chessboard-width": 15, "solutions": 2279184, "language": "C++", "source": "Queen.cxx", "url": "https://gcc.gnu.org", "distribution": "GNU GCC", "version": "gcc 5.x"}, {"duration": 88.66, "chessboard-width": 16, "solutions": 14772512, "language": "C++", "source": "Queen.cxx", "url": "https://gcc.gnu.org", "distribution": "GNU GCC", "version": "gcc 5.x"}, {"duration": 0.0, "chessboard-width": 8, "solutions": 92, "language": "free pascal", "source": "Queen.pas", "url": "http://www.freepascal.org", "distribution": "free pascal", "version": "fpc-3.0.0"}, {"duration": 0.001, "chessboard-width": 9, "solutions": 352, "language": "free pascal", "source": "Queen.pas", "url": "http://www.freepascal.org", "distribution": "free pascal", "version": "fpc-3.0.0"}, {"duration": 0.005, "chessboard-width": 10, "solutions": 724, "language": "free pascal", "source": "Queen.pas", "url": "http://www.freepascal.org", "distribution": "free pascal", "version": "fpc-3.0.0"}, {"duration": 0.065, "chessboard-width": 11, "solutions": 2680, "language": "free pascal", "source": "Queen.pas", "url": "http://www.freepascal.org", "distribution": "free pascal", "version": "fpc-3.0.0"}, {"duration": 0.237, "chessboard-width": 12, "solutions": 14200, "language": "free pascal", "source": "Queen.pas", "url": "http://www.freepascal.org", "distribution": "free pascal", "version": "fpc-3.0.0"}, {"duration": 0.59, "chessboard-width": 13, "solutions": 73712, "language": "free pascal", "source": "Queen.pas", "url": "http://www.freepascal.org", "distribution": "free pascal", "version": "fpc-3.0.0"}, {"duration": 3.396, "chessboard-width": 14, "solutions": 365596, "language": "free pascal", "source": "Queen.pas", "url": "http://www.freepascal.org", "distribution": "free pascal", "version": "fpc-3.0.0"}, {"duration": 23.281, "chessboard-width": 15, "solutions": 2279184, "language": "free pascal", "source": "Queen.pas", "url": "http://www.freepascal.org", "distribution": "free pascal", "version": "fpc-3.0.0"}, {"duration": 0.002, "chessboard-width": 8, "solutions": 92, "language": "Javascript", "source": "Queen_node.js", "url": "https://nodejs.org/en", "distribution": "Node.js", "version": "Node.js 6.9"}, {"duration": 0.003, "chessboard-width": 9, "solutions": 352, "language": "Javascript", "source": "Queen_node.js", "url": "https://nodejs.org/en", "distribution": "Node.js", "version": "Node.js 6.9"}, {"duration": 0.073, "chessboard-width": 10, "solutions": 724, "language": "Javascript", "source": "Queen_node.js", "url": "https://nodejs.org/en", "distribution": "Node.js", "version": "Node.js 6.9"}, {"duration": 0.041, "chessboard-width": 11, "solutions": 2680, "language": "Javascript", "source": "Queen_node.js", "url": "https://nodejs.org/en", "distribution": "Node.js", "version": "Node.js 6.9"}, {"duration": 0.186, "chessboard-width": 12, "solutions": 14200, "language": "Javascript", "source": "Queen_node.js", "url": "https://nodejs.org/en", "distribution": "Node.js", "version": "Node.js 6.9"}, {"duration": 0.662, "chessboard-width": 13, "solutions": 73712, "language": "Javascript", "source": "Queen_node.js", "url": "https://nodejs.org/en", "distribution": "Node.js", "version": "Node.js 6.9"}, {"duration": 3.386, "chessboard-width": 14, "solutions": 365596, "language": "Javascript", "source": "Queen_node.js", "url": "https://nodejs.org/en", "distribution": "Node.js", "version": "Node.js 6.9"}, {"duration": 20.674, "chessboard-width": 15, "solutions": 2279184, "language": "Javascript", "source": "Queen_node.js", "url": "https://nodejs.org/en", "distribution": "Node.js", "version": "Node.js 6.9"}, {"duration": 0.01, "chessboard-width": 8, "solutions": 92, "language": "Perl", "source": "Queen.pl", "url": "https://www.perl.org", "distribution": "Perl", "version": "Perl 5.20"}, {"duration": 0.04, "chessboard-width": 9, "solutions": 352, "language": "Perl", "source": "Queen.pl", "url": "https://www.perl.org", "distribution": "Perl", "version": "Perl 5.20"}, {"duration": 0.38, "chessboard-width": 10, "solutions": 724, "language": "Perl", "source": "Queen.pl", "url": "https://www.perl.org", "distribution": "Perl", "version": "Perl 5.20"}, {"duration": 0.75, "chessboard-width": 11, "solutions": 2680, "language": "Perl", "source": "Queen.pl", "url": "https://www.perl.org", "distribution": "Perl", "version": "Perl 5.20"}, {"duration": 3.74, "chessboard-width": 12, "solutions": 14200, "language": "Perl", "source": "Queen.pl", "url": "https://www.perl.org", "distribution": "Perl", "version": "Perl 5.20"}, {"duration": 21.39, "chessboard-width": 13, "solutions": 73712, "language": "Perl", "source": "Queen.pl", "url": "https://www.perl.org", "distribution": "Perl", "version": "Perl 5.20"}, {"duration": 130.04, "chessboard-width": 14, "solutions": 365596, "language": "Perl", "source": "Queen.pl", "url": "https://www.perl.org", "distribution": "Perl", "version": "Perl 5.20"}, {"duration": 0.0, "chessboard-width": 8, "solutions": 92, "language": "C", "source": "Queen.c", "url": "https://gcc.gnu.org", "distribution": "GNU GCC", "version": "gcc 5.x"}, {"duration": 0.0, "chessboard-width": 9, "solutions": 352, "language": "C", "source": "Queen.c", "url": "https://gcc.gnu.org", "distribution": "GNU GCC", "version": "gcc 5.x"}, {"duration": 0.0, "chessboard-width": 10, "solutions": 724, "language": "C", "source": "Queen.c", "url": "https://gcc.gnu.org", "distribution": "GNU GCC", "version": "gcc 5.x"}, {"duration": 0.01, "chessboard-width": 11, "solutions": 2680, "language": "C", "source": "Queen.c", "url": "https://gcc.gnu.org", "distribution": "GNU GCC", "version": "gcc 5.x"}, {"duration": 0.06, "chessboard-width": 12, "solutions": 14200, "language": "C", "source": "Queen.c", "url": "https://gcc.gnu.org", "distribution": "GNU GCC", "version": "gcc 5.x"}, {"duration": 0.4, "chessboard-width": 13, "solutions": 73712, "language": "C", "source": "Queen.c", "url": "https://gcc.gnu.org", "distribution": "GNU GCC", "version": "gcc 5.x"}, {"duration": 2.14, "chessboard-width": 14, "solutions": 365596, "language": "C", "source": "Queen.c", "url": "https://gcc.gnu.org", "distribution": "GNU GCC", "version": "gcc 5.x"}, {"duration": 13.24, "chessboard-width": 15, "solutions": 2279184, "language": "C", "source": "Queen.c", "url": "https://gcc.gnu.org", "distribution": "GNU GCC", "version": "gcc 5.x"}, {"duration": 90.5, "chessboard-width": 16, "solutions": 14772512, "language": "C", "source": "Queen.c", "url": "https://gcc.gnu.org", "distribution": "GNU GCC", "version": "gcc 5.x"}, {"duration": 0.002478, "chessboard-width": 8, "solutions": 92, "language": "Python", "source": "Queen.py", "url": "https://www.python.org", "distribution": "Python", "version": "Python 3.5"}, {"duration": 0.043517, "chessboard-width": 9, "solutions": 352, "language": "Python", "source": "Queen.py", "url": "https://www.python.org", "distribution": "Python", "version": "Python 3.5"}, {"duration": 0.109924, "chessboard-width": 10, "solutions": 724, "language": "Python", "source": "Queen.py", "url": "https://www.python.org", "distribution": "Python", "version": "Python 3.5"}, {"duration": 0.238306, "chessboard-width": 11, "solutions": 2680, "language": "Python", "source": "Queen.py", "url": "https://www.python.org", "distribution": "Python", "version": "Python 3.5"}, {"duration": 0.9954, "chessboard-width": 12, "solutions": 14200, "language": "Python", "source": "Queen.py", "url": "https://www.python.org", "distribution": "Python", "version": "Python 3.5"}, {"duration": 5.512121, "chessboard-width": 13, "solutions": 73712, "language": "Python", "source": "Queen.py", "url": "https://www.python.org", "distribution": "Python", "version": "Python 3.5"}, {"duration": 29.941906, "chessboard-width": 14, "solutions": 365596, "language": "Python", "source": "Queen.py", "url": "https://www.python.org", "distribution": "Python", "version": "Python 3.5"}, {"duration": 0.02, "chessboard-width": 8, "solutions": 92, "language": "Scala", "source": "Queen.scala", "url": "https://www.scala-lang.org/", "distribution": "Scala", "version": "Scala 2.12.0"}, {"duration": 0.046, "chessboard-width": 9, "solutions": 352, "language": "Scala", "source": "Queen.scala", "url": "https://www.scala-lang.org/", "distribution": "Scala", "version": "Scala 2.12.0"}, {"duration": 0.11, "chessboard-width": 10, "solutions": 724, "language": "Scala", "source": "Queen.scala", "url": "https://www.scala-lang.org/", "distribution": "Scala", "version": "Scala 2.12.0"}, {"duration": 0.186, "chessboard-width": 11, "solutions": 2680, "language": "Scala", "source": "Queen.scala", "url": "https://www.scala-lang.org/", "distribution": "Scala", "version": "Scala 2.12.0"}, {"duration": 0.38, "chessboard-width": 12, "solutions": 14200, "language": "Scala", "source": "Queen.scala", "url": "https://www.scala-lang.org/", "distribution": "Scala", "version": "Scala 2.12.0"}, {"duration": 3.414, "chessboard-width": 13, "solutions": 73712, "language": "Scala", "source": "Queen.scala", "url": "https://www.scala-lang.org/", "distribution": "Scala", "version": "Scala 2.12.0"}, {"duration": 71.332, "chessboard-width": 14, "solutions": 365596, "language": "Scala", "source": "Queen.scala", "url": "https://www.scala-lang.org/", "distribution": "Scala", "version": "Scala 2.12.0"}]